[
  {
    "id": "gv20",
    "names": {
      "en": "Baihui (GV20)",
      "zh": "百会",
      "zh_pinyin": "Bǎi Huì",
      "ja": "百会",
      "ja_reading": "ヒャクエ",
      "fr": "Baihui (VG20)"
    },
    "meridian": "Governing Vessel",
    "location": {
      "en": "Top of the head, at the intersection of the midline and a line connecting the tops of the ears",
      "zh": "头顶正中线与两耳尖连线的交点",
      "ja": "頭頂部、正中線と両耳尖を結ぶ線の交点",
      "fr": "Sommet de la tête, à l'intersection de la ligne médiane et d'une ligne reliant les sommets des oreilles"
    },
    "benefits": {
      "en": ["Relieves headaches", "Calms the mind", "Treats dizziness", "Improves memory"],
      "zh": ["缓解头痛", "安神", "治疗眩晕", "改善记忆"],
      "ja": ["頭痛緩和", "精神安定", "めまい治療", "記憶力向上"],
      "fr": ["Soulage les maux de tête", "Calme l'esprit", "Traite les vertiges", "Améliore la mémoire"]
    },
    "instructions": {
      "en": "Press gently with fingertip for 1-2 minutes. Breathe deeply while pressing.",
      "zh": "用指尖轻轻按压1-2分钟。按压时深呼吸。",
      "ja": "指先で軽く1-2分押し続けます。押しながら深呼吸。",
      "fr": "Appuyez doucement avec le bout du doigt pendant 1-2 minutes. Respirez profondément."
    },
    "precaution": "Use gentle pressure only"
  },
  {
    "id": "ex_hn5",
    "names": {
      "en": "Taiyang (EX-HN5)",
      "zh": "太阳",
      "zh_pinyin": "Tài Yáng",
      "ja": "太陽",
      "ja_reading": "タイヨウ",
      "fr": "Taiyang (Extra)"
    },
    "meridian": "Extra point",
    "location": {
      "en": "In the depression about one finger-width behind the midpoint between the outer edge of the eyebrow and the outer corner of the eye",
      "zh": "眉梢与外眼角之间向后约一横指的凹陷处",
      "ja": "眉の端と目の外角の中間から後ろ約一指幅の凹み",
      "fr": "Dans la dépression à environ un doigt en arrière du point entre l'extrémité du sourcil et le coin externe de l'œil"
    },
    "benefits": {
      "en": ["Relieves headaches", "Reduces eye strain", "Treats migraines", "Clears the mind"],
      "zh": ["缓解头痛", "减轻眼疲劳", "治疗偏头痛", "清醒头脑"],
      "ja": ["頭痛緩和", "眼精疲労軽減", "偏頭痛治療", "頭脳明晰"],
      "fr": ["Soulage les maux de tête", "Réduit la fatigue oculaire", "Traite les migraines", "Clarifie l'esprit"]
    },
    "instructions": {
      "en": "Press and massage in small circles for 1-2 minutes on each side.",
      "zh": "按压并以小圆圈按摩1-2分钟，每侧。",
      "ja": "小円を描くように1-2分按摩します。",
      "fr": "Appuyez et massez en petits cercles pendant 1-2 minutes de chaque côté."
    },
    "precaution": "Use moderate pressure; avoid in cases of head injury"
  },
  {
    "id": "gb20",
    "names": {
      "en": "Fengchi (GB20)",
      "zh": "风池",
      "zh_pinyin": "Fēng Chí",
      "ja": "風池",
      "ja_reading": "フウチ",
      "fr": "Fengchi (VB20)"
    },
    "meridian": "Gallbladder",
    "location": {
      "en": "At the base of the skull, in the depression between the two large neck muscles",
      "zh": "后颈部，枕骨下方，两条大肌肉之间的凹陷处",
      "ja": "後頭部、頭蓋骨の底部、二つの大きな首の筋肉の間の凹み",
      "fr": "À la base du crâne, dans la dépression entre les deux grands muscles du cou"
    },
    "benefits": {
      "en": ["Relieves headaches", "Reduces neck stiffness", "Clears nasal congestion", "Treats colds"],
      "zh": ["缓解头痛", "减轻颈部僵硬", "疏通鼻塞", "治疗感冒"],
      "ja": ["頭痛緩和", "首のこり軽減", "鼻づまり解消", "風邪治療"],
      "fr": ["Soulage les maux de tête", "Réduit la raideur du cou", "Dégage le nez", "Traite les rhumes"]
    },
    "instructions": {
      "en": "Press upward toward the skull with both thumbs for 2-3 minutes.",
      "zh": "用双侧拇指向上朝头骨方向按压2-3分钟。",
      "ja": "両方の親指で頭蓋骨に向かって上に2-3分押し続けます。",
      "fr": "Appuyez vers le haut avec les deux pouces pendant 2-3 minutes."
    },
    "precaution": "Avoid in cases of cervical spine injury"
  },
  {
    "id": "li11",
    "names": {
      "en": "Quchi (LI11)",
      "zh": "曲池",
      "zh_pinyin": "Qū Chí",
      "ja": "曲池",
      "ja_reading": "キョクチ",
      "fr": "Quchi (GI11)"
    },
    "meridian": "Large Intestine",
    "arm": true,
    "location": {
      "en": "At the outer end of the elbow crease when the arm is bent",
      "zh": "肘部弯曲时，肘横纹的外侧端",
      "ja": "肘を曲げた時、肘のシワの外側端",
      "fr": "À l'extrémité externe du pli du coude lorsque le bras est plié"
    },
    "benefits": {
      "en": ["Reduces fever", "Relieves elbow pain", "Treats skin conditions", "Lowers blood pressure"],
      "zh": ["退热", "缓解肘痛", "治疗皮肤病", "降血压"],
      "ja": ["解熱", "肘の痛み緩和", "皮膚疾患治療", "血圧降下"],
      "fr": ["Réduit la fièvre", "Soulage la douleur du coude", "Traite les affections cutanées", "Abaisse la tension"]
    },
    "instructions": {
      "en": "Press firmly with opposite thumb for 2-3 minutes. Effective for fever reduction.",
      "zh": "用对侧拇指用力按压2-3分钟。退热效果好。",
      "ja": "反対側の親指で強く2-3分押し続けます。解熱に効果的。",
      "fr": "Appuyez fermement avec le pouce opposé pendant 2-3 minutes."
    },
    "precaution": "None significant"
  },
  {
    "id": "sp6",
    "names": {
      "en": "Sanyinjiao (SP6)",
      "zh": "三阴交",
      "zh_pinyin": "Sān Yīn Jiāo",
      "ja": "三陰交",
      "ja_reading": "サンインコウ",
      "fr": "Sanyinjiao (Rate6)"
    },
    "meridian": "Spleen",
    "location": {
      "en": "Inner leg, 4 finger-widths above the inner ankle bone, behind the shinbone",
      "zh": "小腿内侧，内踝尖上3寸，胫骨后缘",
      "ja": "脚の内側、内くるぶしから4指幅上、脛骨の後ろ",
      "fr": "Jambe intérieure, 4 largeurs de doigts au-dessus de la malléole interne"
    },
    "benefits": {
      "en": ["Regulates menstruation", "Relieves menstrual cramps", "Improves digestion", "Promotes sleep"],
      "zh": ["调经", "缓解痛经", "改善消化", "促进睡眠"],
      "ja": ["月経調整", "生理痛緩和", "消化改善", "睡眠促進"],
      "fr": ["Règles le cycle menstruel", "Soulage les crampes", "Améliore la digestion", "Favorise le sommeil"]
    },
    "instructions": {
      "en": "Press firmly and massage for 2-3 minutes on each leg. Powerful point for women's health.",
      "zh": "用力按压并按摩2-3分钟，每条腿。妇科要穴。",
      "ja": "強く押し2-3分按摩します。婦人科の要穴。",
      "fr": "Appuyez fermement et massez pendant 2-3 minutes sur chaque jambe."
    },
    "precaution": "AVOID DURING PREGNANCY - may induce contractions"
  },
  {
    "id": "lv3",
    "names": {
      "en": "Taichong (LV3)",
      "zh": "太冲",
      "zh_pinyin": "Tài Chōng",
      "ja": "太衝",
      "ja_reading": "タイショウ",
      "fr": "Taichong (F3)"
    },
    "meridian": "Liver",
    "location": {
      "en": "On the foot, in the depression between the big toe and second toe, about 2 finger-widths up",
      "zh": "足背，大趾与第二趾之间向上约2横指的凹陷处",
      "ja": "足の甲、親指と人差し指の間から約2指幅上の凹み",
      "fr": "Sur le pied, dans la dépression entre le gros orteil et le deuxième orteil"
    },
    "benefits": {
      "en": ["Relieves stress and anger", "Reduces headaches", "Lowers blood pressure", "Regulates menstruation"],
      "zh": ["疏肝理气", "缓解头痛", "降血压", "调经"],
      "ja": ["ストレス解消", "頭痛緩和", "血圧降下", "月経調整"],
      "fr": ["Soulage le stress", "Réduit les maux de tête", "Abaisse la tension", "Règle les menstruations"]
    },
    "instructions": {
      "en": "Press firmly between the tendons for 2-3 minutes on each foot.",
      "zh": "在肌腱之间用力按压2-3分钟，每只脚。",
      "ja": "腱の間を強く2-3分押し続けます。",
      "fr": "Appuyez fermement entre les tendons pendant 2-3 minutes sur chaque pied."
    },
    "precaution": "None significant"
  },
  {
    "id": "ht7",
    "names": {
      "en": "Shenmen (HT7)",
      "zh": "神门",
      "zh_pinyin": "Shén Mén",
      "ja": "神門",
      "ja_reading": "シンモン",
      "fr": "Shenmen (C7)"
    },
    "meridian": "Heart",
    "location": {
      "en": "On the wrist crease, on the pinky side, in the depression next to the tendon",
      "zh": "腕横纹上，小指侧，肌腱旁的凹陷处",
      "ja": "手首のシワ、小指側、腱の横の凹み",
      "fr": "Sur le pli du poignet, côté auriculaire, dans la dépression à côté du tendon"
    },
    "benefits": {
      "en": ["Calms anxiety", "Improves sleep", "Relieves palpitations", "Treats insomnia"],
      "zh": ["安神", "改善睡眠", "缓解心悸", "治疗失眠"],
      "ja": ["不安緩和", "睡眠改善", "動悸緩和", "不眠治療"],
      "fr": ["Calme l'anxiété", "Améliore le sommeil", "Soulège les palpitations", "Traite l'insomnie"]
    },
    "instructions": {
      "en": "Press gently for 2-3 minutes on each wrist. Best done before bed.",
      "zh": "轻轻按压2-3分钟，每侧手腕。睡前效果最佳。",
      "ja": "軽く2-3分押し続けます。寝る前に最適。",
      "fr": "Appuyez doucement pendant 2-3 minutes sur chaque poignet."
    },
    "precaution": "None significant"
  },
  {
    "id": "cv12",
    "names": {
      "en": "Zhongwan (CV12)",
      "zh": "中脘",
      "zh_pinyin": "Zhōng Wǎn",
      "ja": "中脘",
      "ja_reading": "チュウカン",
      "fr": "Zhongwan (VC12)"
    },
    "meridian": "Conception Vessel",
    "location": {
      "en": "On the upper abdomen, 4 finger-widths above the navel, on the midline",
      "zh": "上腹部，肚脐上4寸，正中线上",
      "ja": "上腹部、おへその上4指幅、正中線上",
      "fr": "Sur l'abdomen supérieur, 4 largeurs de doigts au-dessus du nombril"
    },
    "benefits": {
      "en": ["Relieves stomach pain", "Reduces bloating", "Improves digestion", "Treats acid reflux"],
      "zh": ["缓解胃痛", "减少胀气", "改善消化", "治疗反酸"],
      "ja": ["胃痛緩和", "腹部膨満感軽減", "消化改善", "逆流性食道炎治療"],
      "fr": ["Soulage les douleurs d'estomac", "Réduit les ballonnements", "Améliore la digestion", "Traite le reflux acide"]
    },
    "instructions": {
      "en": "Press gently in a clockwise circular motion for 3-5 minutes after meals.",
      "zh": "饭后顺时针轻轻按揉3-5分钟。",
      "ja": "食後に時計回りに軽く3-5分按摩します。",
      "fr": "Appuyez doucement en mouvements circulaires horaires pendant 3-5 minutes après les repas."
    },
    "precaution": "Avoid during pregnancy"
  },
  {
    "id": "cv6",
    "names": {
      "en": "Qihai (CV6)",
      "zh": "气海",
      "zh_pinyin": "Qì Hǎi",
      "ja": "気海",
      "ja_reading": "キカイ",
      "fr": "Qihai (VC6)"
    },
    "meridian": "Conception Vessel",
    "location": {
      "en": "On the lower abdomen, 2 finger-widths below the navel, on the midline",
      "zh": "下腹部，肚脐下1.5寸，正中线上",
      "ja": "下腹部、おへその下2指幅、正中線上",
      "fr": "Sur l'abdomen inférieur, 2 largeurs de doigts sous le nombril"
    },
    "benefits": {
      "en": ["Boosts energy", "Strengthens immunity", "Relieves menstrual pain", "Improves vitality"],
      "zh": ["补气", "增强免疫", "缓解痛经", "改善体质"],
      "ja": ["活力増強", "免疫強化", "生理痛緩和", "体力向上"],
      "fr": ["Booste l'énergie", "Renforce l'immunité", "Soulage les douleurs menstruelles", "Améliore la vitalité"]
    },
    "instructions": {
      "en": "Press and hold for 3-5 minutes. Warm the area with your palm first.",
      "zh": "按压并保持3-5分钟。先用手掌温暖该区域。",
      "ja": "3-5分押し続けます。まず手のひらで温めてから。",
      "fr": "Appuyez et maintenez pendant 3-5 minutes. Réchauffez d'abord la zone avec votre paume."
    },
    "precaution": "Avoid during pregnancy"
  },
  {
    "id": "cv4",
    "names": {
      "en": "Guanyuan (CV4)",
      "zh": "关元",
      "zh_pinyin": "Guān Yuán",
      "ja": "関元",
      "ja_reading": "カンゲン",
      "fr": "Guanyuan (VC4)"
    },
    "meridian": "Conception Vessel",
    "location": {
      "en": "On the lower abdomen, 4 finger-widths below the navel, on the midline",
      "zh": "下腹部，肚脐下3寸，正中线上",
      "ja": "下腹部、おへその下4指幅、正中線上",
      "fr": "Sur l'abdomen inférieur, 4 largeurs de doigts sous le nombril"
    },
    "benefits": {
      "en": ["Strengthens kidney function", "Boosts reproductive health", "Improves energy", "Treats urinary issues"],
      "zh": ["补肾固本", "增强生殖健康", "改善精力", "治疗泌尿问题"],
      "ja": ["腎機能強化", "生殖機能向上", "精力増強", "泌尿器疾患治療"],
      "fr": ["Renforce la fonction rénale", "Améliore la santé reproductive", "Augmente l'énergie", "Traite les problèmes urinaires"]
    },
    "instructions": {
      "en": "Press firmly for 3-5 minutes. Also effective with moxibustion (heat therapy).",
      "zh": "用力按压3-5分钟。艾灸效果更佳。",
      "ja": "強く3-5分押し続けます。お灸も効果的。",
      "fr": "Appuyez fermement pendant 3-5 minutes. Efficace aussi avec moxibustion."
    },
    "precaution": "Avoid during pregnancy"
  }
]
